
{
 "building": [
   {
     "Name": "Avatar: The Last Airbender LEGO Instructions ",
     "legobuilding": "LEGO Instructions 3829 Fire Nation Ship",
     "SetNumber" : "LEGO 3829",
     "SetTheme": "Avatar: The Last Airbender",
     "SetName": "Fire Nation Ship",
     "Year": "2006",
     "imgSrc": "avatar.jpg",
     "imgSrc1": "av1.jpg",
     "imgSrc2": "av2.jpg",
     "imgSrc3": "av3.jpg",
     "imgSrc4": "av4.jpg",
     "imgSrc5": "av5.jpg",
     "imgSrc6": "av6jpg",
     "imgSrc7": "av7.jpg",
     "imgSrc8": "av8.jpg",
     "imgSrc9": "av9.jpg",
     "imgSrc10": "av10.jpg",
     "id": "avatar"
   },

   {
     "Name": "Harry Potter LEGO Instructions ",
     "legobuilding": "LEGO Instructions 4709 Hogwarts Castle",
     "SetNumber" : " LEGO 4709",
     "SetTheme": " Harry Potter",
     "SetName": "Hogwarts Castle",
     "Year": "2001",
     "imgSrc": "hp.jpg",
     "id": "harrypotter"
   },

   {
     "Name": " Sports NBA Basketball LEGO Instructions ",
     "legobuilding": "LEGO Instructions 3432 NBA Challenge",
     "Set Number" : " LEGO 3432",
     "Set Theme": "  Sports NBA Basketball",
     "Set Name": " NBA Challenge",
     "Year": "2003",
     "imgSrc": "nba.jpg",
     "id": "nba"
   }
 ]
}
